gefslim/__init__.py
gefslim/gefslim.py
gefslim/utils.py
gefslim-0.1.1.dist-info/METADATA
gefslim-0.1.1.dist-info/WHEEL
gefslim-0.1.1.dist-info/licenses/LICENSE
gefslim-0.1.1.dist-info/RECORD
